yesno/__init__.py
msl09_yesno-0.1.0.dist-info/METADATA
msl09_yesno-0.1.0.dist-info/WHEEL
msl09_yesno-0.1.0.dist-info/top_level.txt
msl09_yesno-0.1.0.dist-info/RECORD
