Metadata-Version: 2.1
Name: msl09-yesno
Version: 0.1.0
Summary: A module that provides common functions for yes/no CLI queries
Home-page: https://github.com/marceloslacerda/yesno
Author: Marcelo Lacerda
Author-email: marceloslacerda@gmail.com
License: BSD
Keywords: query cli function
Classifier: Development Status :: 4 - Beta
Classifier: Intended Audience :: Developers
Classifier: Topic :: Software Development :: Libraries
Classifier: License :: OSI Approved :: BSD License
Classifier: Environment :: Console
Classifier: Programming Language :: Python :: 3.7
